PlanMaster/PlanMaster.py
PlanMaster-0.0.1.dist-info/LICENSE
PlanMaster-0.0.1.dist-info/METADATA
PlanMaster-0.0.1.dist-info/WHEEL
PlanMaster-0.0.1.dist-info/top_level.txt
PlanMaster-0.0.1.dist-info/RECORD
