Metadata-Version: 2.1
Name: PlanMaster
Version: 0.0.1
Summary: nice calculator
Home-page: https://github.com/duqordl/ScheduleGenius
Download-URL: https://github.com/duqordl/ScheduleGenius
Author: jihyeon
Classifier: Programming Language :: Python :: 3
License-File: LICENSE
